[
    {
        "rnum": 0,
        "cd": "05922",
        "ex": 1,
        "ineum": "몽",
        "in": "몽 : 꿈(몽)",
        "em": 0,
        "rad_id": 36,
        "type": "0",
        "totstroke": 0,
        "stroke": 11,
        "isin": 1,
        "dic": "몽 : 꿈(몽)"
    },
    {
        "rnum": 0,
        "cd": "05924",
        "ex": 1,
        "ineum": "인",
        "in": "인 : 조심할(인)",
        "em": 0,
        "rad_id": 36,
        "type": "0",
        "totstroke": 0,
        "stroke": 11,
        "isin": 1,
        "dic": "린"
    },
    {
        "rnum": 0,
        "cd": "05925",
        "ex": 1,
        "ineum": "과",
        "in": "과 : 많을(과)",
        "em": 0,
        "rad_id": 36,
        "type": "0",
        "totstroke": 0,
        "stroke": 11,
        "isin": 1,
        "dic": "해,화"
    },
    {
        "rnum": 0,
        "cd": "0368b",
        "ex": 0,
        "ineum": "",
        "in": "",
        "em": 0,
        "rad_id": 36,
        "type": "0",
        "totstroke": 0,
        "stroke": 11,
        "isin": 0,
        "dic": "조"
    },
    {
        "rnum": 0,
        "cd": "0368c",
        "ex": 0,
        "ineum": "",
        "in": "",
        "em": 0,
        "rad_id": 36,
        "type": "0",
        "totstroke": 0,
        "stroke": 11,
        "isin": 0,
        "dic": "과,화"
    },
    {
        "rnum": 0,
        "cd": "05923",
        "ex": 0,
        "ineum": "",
        "in": "",
        "em": 0,
        "rad_id": 36,
        "type": "0",
        "totstroke": 0,
        "stroke": 11,
        "isin": 0,
        "dic": "몽"
    },
    {
        "rnum": 0,
        "cd": "f1ee1",
        "ex": 0,
        "ineum": "",
        "in": "",
        "em": 0,
        "rad_id": 36,
        "type": "F",
        "totstroke": 0,
        "stroke": 11,
        "isin": 0,
        "dic": "부"
    },
    {
        "rnum": 0,
        "cd": "f1f69",
        "ex": 0,
        "ineum": "",
        "in": "",
        "em": 0,
        "rad_id": 36,
        "type": "F",
        "totstroke": 0,
        "stroke": 11,
        "isin": 0,
        "dic": "서"
    }
]