[
    {
        "rnum": 0,
        "cd": "03da1",
        "ex": 1,
        "ineum": "화",
        "in": "화",
        "em": 0,
        "rad_id": 86,
        "type": "0",
        "totstroke": 0,
        "stroke": 2,
        "isin": 1,
        "dic": "대,환"
    },
    {
        "rnum": 0,
        "cd": "0706f",
        "ex": 1,
        "ineum": "정",
        "in": "정 : 등잔(정)(燈의 간체자)",
        "em": 0,
        "rad_id": 86,
        "type": "0",
        "totstroke": 0,
        "stroke": 2,
        "isin": 1,
        "dic": "등 : 등잔(등)(燈의 간체자)"
    },
    {
        "rnum": 0,
        "cd": "07070",
        "ex": 1,
        "ineum": "회",
        "in": "회 : 재(회) 활기없을(회)",
        "em": 0,
        "rad_id": 86,
        "type": "0",
        "totstroke": 0,
        "stroke": 2,
        "isin": 1,
        "dic": "희"
    },
    {
        "rnum": 0,
        "cd": "07071",
        "ex": 1,
        "ineum": "초,효",
        "in": "초,효 : 더울(효)",
        "em": 0,
        "rad_id": 86,
        "type": "0",
        "totstroke": 0,
        "stroke": 2,
        "isin": 1,
        "dic": "도 : 태울(도)"
    },
    {
        "rnum": 0,
        "cd": "03da2",
        "ex": 0,
        "ineum": "",
        "in": "",
        "em": 0,
        "rad_id": 86,
        "type": "0",
        "totstroke": 0,
        "stroke": 2,
        "isin": 0,
        "dic": "구,대,화"
    },
    {
        "rnum": 0,
        "cd": "0706e",
        "ex": 0,
        "ineum": "",
        "in": "",
        "em": 0,
        "rad_id": 86,
        "type": "0",
        "totstroke": 0,
        "stroke": 2,
        "isin": 0,
        "dic": "광"
    },
    {
        "rnum": 0,
        "cd": "07072",
        "ex": 0,
        "ineum": "",
        "in": "",
        "em": 0,
        "rad_id": 86,
        "type": "0",
        "totstroke": 0,
        "stroke": 2,
        "isin": 0,
        "dic": "도,효"
    },
    {
        "rnum": 0,
        "cd": "07073",
        "ex": 0,
        "ineum": "",
        "in": "",
        "em": 0,
        "rad_id": 86,
        "type": "0",
        "totstroke": 0,
        "stroke": 2,
        "isin": 0,
        "dic": "휘"
    },
    {
        "rnum": 0,
        "cd": "07087",
        "ex": 0,
        "ineum": "",
        "in": "",
        "em": 0,
        "rad_id": 86,
        "type": "0",
        "totstroke": 0,
        "stroke": 2,
        "isin": 0,
        "dic": "박"
    },
    {
        "rnum": 0,
        "cd": "24183",
        "ex": 0,
        "ineum": "",
        "in": "",
        "em": 0,
        "rad_id": 86,
        "type": "2",
        "totstroke": 0,
        "stroke": 2,
        "isin": 0,
        "dic": "대"
    },
    {
        "rnum": 0,
        "cd": "24184",
        "ex": 0,
        "ineum": "",
        "in": "",
        "em": 0,
        "rad_id": 86,
        "type": "2",
        "totstroke": 0,
        "stroke": 2,
        "isin": 0,
        "dic": "화,회"
    },
    {
        "rnum": 0,
        "cd": "24185",
        "ex": 0,
        "ineum": "",
        "in": "",
        "em": 0,
        "rad_id": 86,
        "type": "2",
        "totstroke": 0,
        "stroke": 2,
        "isin": 0,
        "dic": "사"
    },
    {
        "rnum": 0,
        "cd": "24186",
        "ex": 0,
        "ineum": "",
        "in": "",
        "em": 0,
        "rad_id": 86,
        "type": "2",
        "totstroke": 0,
        "stroke": 2,
        "isin": 0,
        "dic": "회"
    },
    {
        "rnum": 0,
        "cd": "2418a",
        "ex": 0,
        "ineum": "",
        "in": "",
        "em": 0,
        "rad_id": 86,
        "type": "2",
        "totstroke": 0,
        "stroke": 2,
        "isin": 0,
        "dic": "복"
    },
    {
        "rnum": 0,
        "cd": "f01ec",
        "ex": 0,
        "ineum": "",
        "in": "",
        "em": 0,
        "rad_id": 86,
        "type": "F",
        "totstroke": 0,
        "stroke": 2,
        "isin": 0,
        "dic": "광"
    },
    {
        "rnum": 0,
        "cd": "f0a84",
        "ex": 0,
        "ineum": "",
        "in": "",
        "em": 0,
        "rad_id": 86,
        "type": "F",
        "totstroke": 0,
        "stroke": 2,
        "isin": 0,
        "dic": "승"
    },
    {
        "rnum": 0,
        "cd": "f2abf",
        "ex": 0,
        "ineum": "",
        "in": "",
        "em": 0,
        "rad_id": 86,
        "type": "F",
        "totstroke": 0,
        "stroke": 2,
        "isin": 0,
        "dic": "칠"
    }
]