[
    {
        "rnum": 0,
        "cd": "07228",
        "ex": 1,
        "ineum": "찬",
        "in": "찬 : 부뚜막(찬)",
        "em": 0,
        "rad_id": 86,
        "type": "0",
        "totstroke": 0,
        "stroke": 25,
        "isin": 1,
        "dic": ""
    },
    {
        "rnum": 0,
        "cd": "244ed",
        "ex": 0,
        "ineum": "",
        "in": "",
        "em": 0,
        "rad_id": 86,
        "type": "2",
        "totstroke": 0,
        "stroke": 25,
        "isin": 0,
        "dic": "울"
    }
]