[
    {
        "rnum": 0,
        "cd": "2453c",
        "ex": 0,
        "ineum": "",
        "in": "",
        "em": 0,
        "rad_id": 87,
        "type": "2",
        "totstroke": 0,
        "stroke": 13,
        "isin": 0,
        "dic": "토"
    },
    {
        "rnum": 0,
        "cd": "f1133",
        "ex": 0,
        "ineum": "",
        "in": "",
        "em": 0,
        "rad_id": 87,
        "type": "F",
        "totstroke": 0,
        "stroke": 13,
        "isin": 0,
        "dic": "정"
    },
    {
        "rnum": 0,
        "cd": "f27c4",
        "ex": 0,
        "ineum": "",
        "in": "",
        "em": 0,
        "rad_id": 87,
        "type": "F",
        "totstroke": 0,
        "stroke": 13,
        "isin": 0,
        "dic": "정"
    },
    {
        "rnum": 0,
        "cd": "f27c5",
        "ex": 0,
        "ineum": "",
        "in": "",
        "em": 0,
        "rad_id": 87,
        "type": "F",
        "totstroke": 0,
        "stroke": 13,
        "isin": 0,
        "dic": "정"
    },
    {
        "rnum": 0,
        "cd": "f2b65",
        "ex": 0,
        "ineum": "",
        "in": "",
        "em": 0,
        "rad_id": 87,
        "type": "F",
        "totstroke": 0,
        "stroke": 13,
        "isin": 0,
        "dic": "해"
    },
    {
        "rnum": 0,
        "cd": "f2f18",
        "ex": 0,
        "ineum": "",
        "in": "",
        "em": 0,
        "rad_id": 87,
        "type": "F",
        "totstroke": 0,
        "stroke": 13,
        "isin": 0,
        "dic": "서"
    },
    {
        "rnum": 0,
        "cd": "f32e3",
        "ex": 0,
        "ineum": "",
        "in": "",
        "em": 0,
        "rad_id": 87,
        "type": "F",
        "totstroke": 0,
        "stroke": 13,
        "isin": 0,
        "dic": "정"
    }
]