[
    {
        "rnum": 0,
        "cd": "0770e",
        "ex": 1,
        "ineum": "시",
        "in": "시",
        "em": 0,
        "rad_id": 109,
        "type": "0",
        "totstroke": 0,
        "stroke": 5,
        "isin": 1,
        "dic": ""
    },
    {
        "rnum": 0,
        "cd": "07710",
        "ex": 1,
        "ineum": "정",
        "in": "정 : 홀로볼(정)",
        "em": 0,
        "rad_id": 109,
        "type": "0",
        "totstroke": 0,
        "stroke": 5,
        "isin": 1,
        "dic": ""
    },
    {
        "rnum": 0,
        "cd": "07715",
        "ex": 1,
        "ineum": "진",
        "in": "진 : 한껏볼(진) 진중할(진)",
        "em": 0,
        "rad_id": 109,
        "type": "0",
        "totstroke": 0,
        "stroke": 5,
        "isin": 1,
        "dic": ""
    },
    {
        "rnum": 0,
        "cd": "0771a",
        "ex": 1,
        "ineum": "생",
        "in": "생 : 흐릴(생)",
        "em": 0,
        "rad_id": 109,
        "type": "0",
        "totstroke": 0,
        "stroke": 5,
        "isin": 1,
        "dic": ""
    },
    {
        "rnum": 0,
        "cd": "0771b",
        "ex": 1,
        "ineum": "매",
        "in": "매 : 눈희미할(매)",
        "em": 0,
        "rad_id": 109,
        "type": "0",
        "totstroke": 0,
        "stroke": 5,
        "isin": 1,
        "dic": "미,조"
    },
    {
        "rnum": 0,
        "cd": "0771e",
        "ex": 1,
        "ineum": "진",
        "in": "진 : 참(진)",
        "em": 0,
        "rad_id": 109,
        "type": "0",
        "totstroke": 0,
        "stroke": 5,
        "isin": 1,
        "dic": "진 : 참(진)"
    },
    {
        "rnum": 0,
        "cd": "0771f",
        "ex": 1,
        "ineum": "진",
        "in": "진 : 참(진)",
        "em": 0,
        "rad_id": 109,
        "type": "0",
        "totstroke": 0,
        "stroke": 5,
        "isin": 1,
        "dic": "진 : 참(진)"
    },
    {
        "rnum": 0,
        "cd": "07720",
        "ex": 1,
        "ineum": "면,민",
        "in": "면,민 : 잘(면)",
        "em": 0,
        "rad_id": 109,
        "type": "0",
        "totstroke": 0,
        "stroke": 5,
        "isin": 1,
        "dic": "안"
    },
    {
        "rnum": 0,
        "cd": "07725",
        "ex": 1,
        "ineum": "자",
        "in": "자 : 흘겨볼(자)",
        "em": 0,
        "rad_id": 109,
        "type": "0",
        "totstroke": 0,
        "stroke": 5,
        "isin": 1,
        "dic": "제 : 눈가(제) 눈초리(제)"
    },
    {
        "rnum": 0,
        "cd": "07726",
        "ex": 1,
        "ineum": "자",
        "in": "자 : 눈초리(자)",
        "em": 0,
        "rad_id": 109,
        "type": "0",
        "totstroke": 0,
        "stroke": 5,
        "isin": 1,
        "dic": "제 : 눈초리(제)"
    },
    {
        "rnum": 0,
        "cd": "07728",
        "ex": 1,
        "ineum": "잡",
        "in": "잡 : 눈깜박일(잡)",
        "em": 0,
        "rad_id": 109,
        "type": "0",
        "totstroke": 0,
        "stroke": 5,
        "isin": 1,
        "dic": ""
    },
    {
        "rnum": 0,
        "cd": "07729",
        "ex": 1,
        "ineum": "현",
        "in": "현 : 아찔할(현) 현혹할(현)",
        "em": 0,
        "rad_id": 109,
        "type": "0",
        "totstroke": 0,
        "stroke": 5,
        "isin": 1,
        "dic": "현 : 아찔할(현) 현 혹할(현)"
    },
    {
        "rnum": 0,
        "cd": "0401f",
        "ex": 0,
        "ineum": "",
        "in": "",
        "em": 0,
        "rad_id": 109,
        "type": "0",
        "totstroke": 0,
        "stroke": 5,
        "isin": 0,
        "dic": "비"
    },
    {
        "rnum": 0,
        "cd": "04020",
        "ex": 0,
        "ineum": "",
        "in": "",
        "em": 0,
        "rad_id": 109,
        "type": "0",
        "totstroke": 0,
        "stroke": 5,
        "isin": 0,
        "dic": "구"
    },
    {
        "rnum": 0,
        "cd": "04021",
        "ex": 0,
        "ineum": "",
        "in": "",
        "em": 0,
        "rad_id": 109,
        "type": "0",
        "totstroke": 0,
        "stroke": 5,
        "isin": 0,
        "dic": "점"
    },
    {
        "rnum": 0,
        "cd": "04022",
        "ex": 0,
        "ineum": "",
        "in": "",
        "em": 0,
        "rad_id": 109,
        "type": "0",
        "totstroke": 0,
        "stroke": 5,
        "isin": 0,
        "dic": "순"
    },
    {
        "rnum": 0,
        "cd": "04023",
        "ex": 0,
        "ineum": "",
        "in": "",
        "em": 0,
        "rad_id": 109,
        "type": "0",
        "totstroke": 0,
        "stroke": 5,
        "isin": 0,
        "dic": "비"
    },
    {
        "rnum": 0,
        "cd": "04024",
        "ex": 0,
        "ineum": "",
        "in": "",
        "em": 0,
        "rad_id": 109,
        "type": "0",
        "totstroke": 0,
        "stroke": 5,
        "isin": 0,
        "dic": "무"
    },
    {
        "rnum": 0,
        "cd": "04026",
        "ex": 0,
        "ineum": "",
        "in": "",
        "em": 0,
        "rad_id": 109,
        "type": "0",
        "totstroke": 0,
        "stroke": 5,
        "isin": 0,
        "dic": "고"
    },
    {
        "rnum": 0,
        "cd": "0770f",
        "ex": 0,
        "ineum": "",
        "in": "",
        "em": 0,
        "rad_id": 109,
        "type": "0",
        "totstroke": 0,
        "stroke": 5,
        "isin": 0,
        "dic": "앙,영 : 눈어두울(앙) 눈흘길(앙) 볼 (영)"
    },
    {
        "rnum": 0,
        "cd": "07711",
        "ex": 0,
        "ineum": "",
        "in": "",
        "em": 0,
        "rad_id": 109,
        "type": "0",
        "totstroke": 0,
        "stroke": 5,
        "isin": 0,
        "dic": "요,유 : 깊숙할(요)  아득할(유)"
    },
    {
        "rnum": 0,
        "cd": "07712",
        "ex": 0,
        "ineum": "",
        "in": "",
        "em": 0,
        "rad_id": 109,
        "type": "0",
        "totstroke": 0,
        "stroke": 5,
        "isin": 0,
        "dic": "신 : 눈부릅뜰(신)  시선을끌(신) 새짐 승놀랄(신)"
    },
    {
        "rnum": 0,
        "cd": "07713",
        "ex": 0,
        "ineum": "",
        "in": "",
        "em": 0,
        "rad_id": 109,
        "type": "0",
        "totstroke": 0,
        "stroke": 5,
        "isin": 0,
        "dic": "활 : 볼(활) 높이볼 (활)"
    },
    {
        "rnum": 0,
        "cd": "07714",
        "ex": 0,
        "ineum": "",
        "in": "",
        "em": 0,
        "rad_id": 109,
        "type": "0",
        "totstroke": 0,
        "stroke": 5,
        "isin": 0,
        "dic": "답"
    },
    {
        "rnum": 0,
        "cd": "07716",
        "ex": 0,
        "ineum": "",
        "in": "",
        "em": 0,
        "rad_id": 109,
        "type": "0",
        "totstroke": 0,
        "stroke": 5,
        "isin": 0,
        "dic": "황 : 볼(황)"
    },
    {
        "rnum": 0,
        "cd": "07717",
        "ex": 0,
        "ineum": "",
        "in": "",
        "em": 0,
        "rad_id": 109,
        "type": "0",
        "totstroke": 0,
        "stroke": 5,
        "isin": 0,
        "dic": "구 : 휘휘둘어볼(구)"
    },
    {
        "rnum": 0,
        "cd": "07718",
        "ex": 0,
        "ineum": "",
        "in": "",
        "em": 0,
        "rad_id": 109,
        "type": "0",
        "totstroke": 0,
        "stroke": 5,
        "isin": 0,
        "dic": "신"
    },
    {
        "rnum": 0,
        "cd": "07719",
        "ex": 0,
        "ineum": "",
        "in": "",
        "em": 0,
        "rad_id": 109,
        "type": "0",
        "totstroke": 0,
        "stroke": 5,
        "isin": 0,
        "dic": "이,치 : 눈여겨볼(치) 땅이름(이)"
    },
    {
        "rnum": 0,
        "cd": "0771c",
        "ex": 0,
        "ineum": "",
        "in": "",
        "em": 0,
        "rad_id": 109,
        "type": "0",
        "totstroke": 0,
        "stroke": 5,
        "isin": 0,
        "dic": "말 : 눈희미할(말)  무릅쓸(말)"
    },
    {
        "rnum": 0,
        "cd": "0771d",
        "ex": 0,
        "ineum": "",
        "in": "",
        "em": 0,
        "rad_id": 109,
        "type": "0",
        "totstroke": 0,
        "stroke": 5,
        "isin": 0,
        "dic": "저 : 눈번쩍뜰(저)  부릅뜰(저)"
    },
    {
        "rnum": 0,
        "cd": "07721",
        "ex": 0,
        "ineum": "",
        "in": "",
        "em": 0,
        "rad_id": 109,
        "type": "0",
        "totstroke": 0,
        "stroke": 5,
        "isin": 0,
        "dic": "시,저 : 보는모양(시)"
    },
    {
        "rnum": 0,
        "cd": "07722",
        "ex": 0,
        "ineum": "",
        "in": "",
        "em": 0,
        "rad_id": 109,
        "type": "0",
        "totstroke": 0,
        "stroke": 5,
        "isin": 0,
        "dic": "완,원 : 눈멀(원)  우물마를(원)"
    },
    {
        "rnum": 0,
        "cd": "07723",
        "ex": 0,
        "ineum": "",
        "in": "",
        "em": 0,
        "rad_id": 109,
        "type": "0",
        "totstroke": 0,
        "stroke": 5,
        "isin": 0,
        "dic": "질 : 눈뒤죽거릴(질)  눈비뚤(질)"
    },
    {
        "rnum": 0,
        "cd": "07724",
        "ex": 0,
        "ineum": "",
        "in": "",
        "em": 0,
        "rad_id": 109,
        "type": "0",
        "totstroke": 0,
        "stroke": 5,
        "isin": 0,
        "dic": "닐,이"
    },
    {
        "rnum": 0,
        "cd": "07727",
        "ex": 0,
        "ineum": "",
        "in": "",
        "em": 0,
        "rad_id": 109,
        "type": "0",
        "totstroke": 0,
        "stroke": 5,
        "isin": 0,
        "dic": "소,조,초 : 눈으로사 람희롱할(초)"
    },
    {
        "rnum": 0,
        "cd": "0772a",
        "ex": 0,
        "ineum": "",
        "in": "",
        "em": 0,
        "rad_id": 109,
        "type": "0",
        "totstroke": 0,
        "stroke": 5,
        "isin": 0,
        "dic": "병 : 눈밝을(병)"
    },
    {
        "rnum": 0,
        "cd": "0772b",
        "ex": 0,
        "ineum": "",
        "in": "",
        "em": 0,
        "rad_id": 109,
        "type": "0",
        "totstroke": 0,
        "stroke": 5,
        "isin": 0,
        "dic": "미,반 : 마귀에홀릴(미) 어지러울(몌) 와 同字"
    },
    {
        "rnum": 0,
        "cd": "0772c",
        "ex": 0,
        "ineum": "",
        "in": "",
        "em": 0,
        "rad_id": 109,
        "type": "0",
        "totstroke": 0,
        "stroke": 5,
        "isin": 0,
        "dic": "롱"
    },
    {
        "rnum": 0,
        "cd": "0773f",
        "ex": 0,
        "ineum": "",
        "in": "",
        "em": 0,
        "rad_id": 109,
        "type": "0",
        "totstroke": 0,
        "stroke": 5,
        "isin": 0,
        "dic": "맥,영,창"
    },
    {
        "rnum": 0,
        "cd": "25131",
        "ex": 0,
        "ineum": "",
        "in": "",
        "em": 0,
        "rad_id": 109,
        "type": "2",
        "totstroke": 0,
        "stroke": 5,
        "isin": 0,
        "dic": "비"
    },
    {
        "rnum": 0,
        "cd": "25134",
        "ex": 0,
        "ineum": "",
        "in": "",
        "em": 0,
        "rad_id": 109,
        "type": "2",
        "totstroke": 0,
        "stroke": 5,
        "isin": 0,
        "dic": "혈"
    },
    {
        "rnum": 0,
        "cd": "25135",
        "ex": 0,
        "ineum": "",
        "in": "",
        "em": 0,
        "rad_id": 109,
        "type": "2",
        "totstroke": 0,
        "stroke": 5,
        "isin": 0,
        "dic": "휼"
    },
    {
        "rnum": 0,
        "cd": "25136",
        "ex": 0,
        "ineum": "",
        "in": "",
        "em": 0,
        "rad_id": 109,
        "type": "2",
        "totstroke": 0,
        "stroke": 5,
        "isin": 0,
        "dic": "사"
    },
    {
        "rnum": 0,
        "cd": "25137",
        "ex": 0,
        "ineum": "",
        "in": "",
        "em": 0,
        "rad_id": 109,
        "type": "2",
        "totstroke": 0,
        "stroke": 5,
        "isin": 0,
        "dic": "구"
    },
    {
        "rnum": 0,
        "cd": "25138",
        "ex": 0,
        "ineum": "",
        "in": "",
        "em": 0,
        "rad_id": 109,
        "type": "2",
        "totstroke": 0,
        "stroke": 5,
        "isin": 0,
        "dic": "묘"
    },
    {
        "rnum": 0,
        "cd": "2513a",
        "ex": 0,
        "ineum": "",
        "in": "",
        "em": 0,
        "rad_id": 109,
        "type": "2",
        "totstroke": 0,
        "stroke": 5,
        "isin": 0,
        "dic": "글,질"
    },
    {
        "rnum": 0,
        "cd": "2513d",
        "ex": 0,
        "ineum": "",
        "in": "",
        "em": 0,
        "rad_id": 109,
        "type": "2",
        "totstroke": 0,
        "stroke": 5,
        "isin": 0,
        "dic": "니"
    },
    {
        "rnum": 0,
        "cd": "2513e",
        "ex": 0,
        "ineum": "",
        "in": "",
        "em": 0,
        "rad_id": 109,
        "type": "2",
        "totstroke": 0,
        "stroke": 5,
        "isin": 0,
        "dic": "성"
    },
    {
        "rnum": 0,
        "cd": "25141",
        "ex": 0,
        "ineum": "",
        "in": "",
        "em": 0,
        "rad_id": 109,
        "type": "2",
        "totstroke": 0,
        "stroke": 5,
        "isin": 0,
        "dic": "조"
    },
    {
        "rnum": 0,
        "cd": "25144",
        "ex": 0,
        "ineum": "",
        "in": "",
        "em": 0,
        "rad_id": 109,
        "type": "2",
        "totstroke": 0,
        "stroke": 5,
        "isin": 0,
        "dic": "노"
    },
    {
        "rnum": 0,
        "cd": "25153",
        "ex": 0,
        "ineum": "",
        "in": "",
        "em": 0,
        "rad_id": 109,
        "type": "2",
        "totstroke": 0,
        "stroke": 5,
        "isin": 0,
        "dic": "시"
    },
    {
        "rnum": 0,
        "cd": "f04d3",
        "ex": 0,
        "ineum": "",
        "in": "",
        "em": 0,
        "rad_id": 109,
        "type": "F",
        "totstroke": 0,
        "stroke": 5,
        "isin": 0,
        "dic": "영"
    },
    {
        "rnum": 0,
        "cd": "f083e",
        "ex": 0,
        "ineum": "",
        "in": "",
        "em": 0,
        "rad_id": 109,
        "type": "F",
        "totstroke": 0,
        "stroke": 5,
        "isin": 0,
        "dic": "서"
    },
    {
        "rnum": 0,
        "cd": "f0f62",
        "ex": 0,
        "ineum": "",
        "in": "",
        "em": 0,
        "rad_id": 109,
        "type": "F",
        "totstroke": 0,
        "stroke": 5,
        "isin": 0,
        "dic": "윤"
    },
    {
        "rnum": 0,
        "cd": "f11c5",
        "ex": 0,
        "ineum": "",
        "in": "",
        "em": 0,
        "rad_id": 109,
        "type": "F",
        "totstroke": 0,
        "stroke": 5,
        "isin": 0,
        "dic": "주"
    },
    {
        "rnum": 0,
        "cd": "f12e5",
        "ex": 0,
        "ineum": "",
        "in": "",
        "em": 0,
        "rad_id": 109,
        "type": "F",
        "totstroke": 0,
        "stroke": 5,
        "isin": 0,
        "dic": "진"
    },
    {
        "rnum": 0,
        "cd": "f12e6",
        "ex": 0,
        "ineum": "",
        "in": "",
        "em": 0,
        "rad_id": 109,
        "type": "F",
        "totstroke": 0,
        "stroke": 5,
        "isin": 0,
        "dic": "진"
    },
    {
        "rnum": 0,
        "cd": "f145a",
        "ex": 0,
        "ineum": "",
        "in": "",
        "em": 0,
        "rad_id": 109,
        "type": "F",
        "totstroke": 0,
        "stroke": 5,
        "isin": 0,
        "dic": "춘"
    },
    {
        "rnum": 0,
        "cd": "f1d4d",
        "ex": 0,
        "ineum": "",
        "in": "",
        "em": 0,
        "rad_id": 109,
        "type": "F",
        "totstroke": 0,
        "stroke": 5,
        "isin": 0,
        "dic": "무"
    },
    {
        "rnum": 0,
        "cd": "f23a8",
        "ex": 0,
        "ineum": "",
        "in": "",
        "em": 0,
        "rad_id": 109,
        "type": "F",
        "totstroke": 0,
        "stroke": 5,
        "isin": 0,
        "dic": "영"
    },
    {
        "rnum": 0,
        "cd": "f2511",
        "ex": 0,
        "ineum": "",
        "in": "",
        "em": 0,
        "rad_id": 109,
        "type": "F",
        "totstroke": 0,
        "stroke": 5,
        "isin": 0,
        "dic": "우"
    },
    {
        "rnum": 0,
        "cd": "f27b9",
        "ex": 0,
        "ineum": "",
        "in": "",
        "em": 0,
        "rad_id": 109,
        "type": "F",
        "totstroke": 0,
        "stroke": 5,
        "isin": 0,
        "dic": "정"
    },
    {
        "rnum": 0,
        "cd": "f2aaa",
        "ex": 0,
        "ineum": "",
        "in": "",
        "em": 0,
        "rad_id": 109,
        "type": "F",
        "totstroke": 0,
        "stroke": 5,
        "isin": 0,
        "dic": "출"
    },
    {
        "rnum": 0,
        "cd": "f2f36",
        "ex": 0,
        "ineum": "",
        "in": "",
        "em": 0,
        "rad_id": 109,
        "type": "F",
        "totstroke": 0,
        "stroke": 5,
        "isin": 0,
        "dic": "성"
    }
]