[
    {
        "rnum": 0,
        "cd": "07cc5",
        "ex": 1,
        "ineum": "유",
        "in": "유 : 섞을(유)",
        "em": 0,
        "rad_id": 119,
        "type": "0",
        "totstroke": 0,
        "stroke": 9,
        "isin": 1,
        "dic": ""
    },
    {
        "rnum": 0,
        "cd": "07cca",
        "ex": 1,
        "ineum": "호",
        "in": "호 : 풀(호) 바를(호)",
        "em": 0,
        "rad_id": 119,
        "type": "0",
        "totstroke": 0,
        "stroke": 9,
        "isin": 1,
        "dic": "호 : 풀(호) 바를(호)"
    },
    {
        "rnum": 0,
        "cd": "04293",
        "ex": 0,
        "ineum": "",
        "in": "",
        "em": 0,
        "rad_id": 119,
        "type": "0",
        "totstroke": 0,
        "stroke": 9,
        "isin": 0,
        "dic": "시,지"
    },
    {
        "rnum": 0,
        "cd": "04294",
        "ex": 0,
        "ineum": "",
        "in": "",
        "em": 0,
        "rad_id": 119,
        "type": "0",
        "totstroke": 0,
        "stroke": 9,
        "isin": 0,
        "dic": "영"
    },
    {
        "rnum": 0,
        "cd": "04295",
        "ex": 0,
        "ineum": "",
        "in": "",
        "em": 0,
        "rad_id": 119,
        "type": "0",
        "totstroke": 0,
        "stroke": 9,
        "isin": 0,
        "dic": "건,전"
    },
    {
        "rnum": 0,
        "cd": "04296",
        "ex": 0,
        "ineum": "",
        "in": "",
        "em": 0,
        "rad_id": 119,
        "type": "0",
        "totstroke": 0,
        "stroke": 9,
        "isin": 0,
        "dic": "남"
    },
    {
        "rnum": 0,
        "cd": "04297",
        "ex": 0,
        "ineum": "",
        "in": "",
        "em": 0,
        "rad_id": 119,
        "type": "0",
        "totstroke": 0,
        "stroke": 9,
        "isin": 0,
        "dic": "황"
    },
    {
        "rnum": 0,
        "cd": "04298",
        "ex": 0,
        "ineum": "",
        "in": "",
        "em": 0,
        "rad_id": 119,
        "type": "0",
        "totstroke": 0,
        "stroke": 9,
        "isin": 0,
        "dic": "주"
    },
    {
        "rnum": 0,
        "cd": "04299",
        "ex": 0,
        "ineum": "",
        "in": "",
        "em": 0,
        "rad_id": 119,
        "type": "0",
        "totstroke": 0,
        "stroke": 9,
        "isin": 0,
        "dic": "연"
    },
    {
        "rnum": 0,
        "cd": "042a0",
        "ex": 0,
        "ineum": "",
        "in": "",
        "em": 0,
        "rad_id": 119,
        "type": "0",
        "totstroke": 0,
        "stroke": 9,
        "isin": 0,
        "dic": "희"
    },
    {
        "rnum": 0,
        "cd": "07cc2",
        "ex": 0,
        "ineum": "",
        "in": "",
        "em": 0,
        "rad_id": 119,
        "type": "0",
        "totstroke": 0,
        "stroke": 9,
        "isin": 0,
        "dic": "삼 : 섞일(삼) 쌀가 루(삼)"
    },
    {
        "rnum": 0,
        "cd": "07cc3",
        "ex": 0,
        "ineum": "",
        "in": "",
        "em": 0,
        "rad_id": 119,
        "type": "0",
        "totstroke": 0,
        "stroke": 9,
        "isin": 0,
        "dic": "당 : 정미(당)"
    },
    {
        "rnum": 0,
        "cd": "07cc4",
        "ex": 0,
        "ineum": "",
        "in": "",
        "em": 0,
        "rad_id": 119,
        "type": "0",
        "totstroke": 0,
        "stroke": 9,
        "isin": 0,
        "dic": "변"
    },
    {
        "rnum": 0,
        "cd": "07cc6",
        "ex": 0,
        "ineum": "",
        "in": "",
        "em": 0,
        "rad_id": 119,
        "type": "0",
        "totstroke": 0,
        "stroke": 9,
        "isin": 0,
        "dic": "면 : 가루(면)"
    },
    {
        "rnum": 0,
        "cd": "07cc7",
        "ex": 0,
        "ineum": "",
        "in": "",
        "em": 0,
        "rad_id": 119,
        "type": "0",
        "totstroke": 0,
        "stroke": 9,
        "isin": 0,
        "dic": "후 : 말린밥(후)"
    },
    {
        "rnum": 0,
        "cd": "07cc8",
        "ex": 0,
        "ineum": "",
        "in": "",
        "em": 0,
        "rad_id": 119,
        "type": "0",
        "totstroke": 0,
        "stroke": 9,
        "isin": 0,
        "dic": "서 : 양식(서)"
    },
    {
        "rnum": 0,
        "cd": "07cc9",
        "ex": 0,
        "ineum": "",
        "in": "",
        "em": 0,
        "rad_id": 119,
        "type": "0",
        "totstroke": 0,
        "stroke": 9,
        "isin": 0,
        "dic": "종 : 송편(종)"
    },
    {
        "rnum": 0,
        "cd": "07ccb",
        "ex": 0,
        "ineum": "",
        "in": "",
        "em": 0,
        "rad_id": 119,
        "type": "0",
        "totstroke": 0,
        "stroke": 9,
        "isin": 0,
        "dic": "전 : 쌀전붙일(전)"
    },
    {
        "rnum": 0,
        "cd": "07ccc",
        "ex": 0,
        "ineum": "",
        "in": "",
        "em": 0,
        "rad_id": 119,
        "type": "0",
        "totstroke": 0,
        "stroke": 9,
        "isin": 0,
        "dic": "잠 : 참파(잠/찰)"
    },
    {
        "rnum": 0,
        "cd": "07ccd",
        "ex": 0,
        "ineum": "",
        "in": "",
        "em": 0,
        "rad_id": 119,
        "type": "0",
        "totstroke": 0,
        "stroke": 9,
        "isin": 0,
        "dic": "자 : 인절미(자)"
    },
    {
        "rnum": 0,
        "cd": "07cce",
        "ex": 0,
        "ineum": "",
        "in": "",
        "em": 0,
        "rad_id": 119,
        "type": "0",
        "totstroke": 0,
        "stroke": 9,
        "isin": 0,
        "dic": "리 : 센티미터(리)"
    },
    {
        "rnum": 0,
        "cd": "25ec1",
        "ex": 0,
        "ineum": "",
        "in": "",
        "em": 0,
        "rad_id": 119,
        "type": "2",
        "totstroke": 0,
        "stroke": 9,
        "isin": 0,
        "dic": "단"
    },
    {
        "rnum": 0,
        "cd": "25ec2",
        "ex": 0,
        "ineum": "",
        "in": "",
        "em": 0,
        "rad_id": 119,
        "type": "2",
        "totstroke": 0,
        "stroke": 9,
        "isin": 0,
        "dic": "란"
    },
    {
        "rnum": 0,
        "cd": "25ec3",
        "ex": 0,
        "ineum": "",
        "in": "",
        "em": 0,
        "rad_id": 119,
        "type": "2",
        "totstroke": 0,
        "stroke": 9,
        "isin": 0,
        "dic": "려"
    },
    {
        "rnum": 0,
        "cd": "25ec4",
        "ex": 0,
        "ineum": "",
        "in": "",
        "em": 0,
        "rad_id": 119,
        "type": "2",
        "totstroke": 0,
        "stroke": 9,
        "isin": 0,
        "dic": "개"
    },
    {
        "rnum": 0,
        "cd": "25ec5",
        "ex": 0,
        "ineum": "",
        "in": "",
        "em": 0,
        "rad_id": 119,
        "type": "2",
        "totstroke": 0,
        "stroke": 9,
        "isin": 0,
        "dic": "퍅"
    },
    {
        "rnum": 0,
        "cd": "25ec6",
        "ex": 0,
        "ineum": "",
        "in": "",
        "em": 0,
        "rad_id": 119,
        "type": "2",
        "totstroke": 0,
        "stroke": 9,
        "isin": 0,
        "dic": "속"
    },
    {
        "rnum": 0,
        "cd": "25ec9",
        "ex": 0,
        "ineum": "",
        "in": "",
        "em": 0,
        "rad_id": 119,
        "type": "2",
        "totstroke": 0,
        "stroke": 9,
        "isin": 0,
        "dic": "갈"
    },
    {
        "rnum": 0,
        "cd": "25eca",
        "ex": 0,
        "ineum": "",
        "in": "",
        "em": 0,
        "rad_id": 119,
        "type": "2",
        "totstroke": 0,
        "stroke": 9,
        "isin": 0,
        "dic": "리"
    },
    {
        "rnum": 0,
        "cd": "25ecf",
        "ex": 0,
        "ineum": "",
        "in": "",
        "em": 0,
        "rad_id": 119,
        "type": "2",
        "totstroke": 0,
        "stroke": 9,
        "isin": 0,
        "dic": "서"
    },
    {
        "rnum": 0,
        "cd": "25ed0",
        "ex": 0,
        "ineum": "",
        "in": "",
        "em": 0,
        "rad_id": 119,
        "type": "2",
        "totstroke": 0,
        "stroke": 9,
        "isin": 0,
        "dic": "시"
    },
    {
        "rnum": 0,
        "cd": "25ed1",
        "ex": 0,
        "ineum": "",
        "in": "",
        "em": 0,
        "rad_id": 119,
        "type": "2",
        "totstroke": 0,
        "stroke": 9,
        "isin": 0,
        "dic": "우"
    },
    {
        "rnum": 0,
        "cd": "25ed2",
        "ex": 0,
        "ineum": "",
        "in": "",
        "em": 0,
        "rad_id": 119,
        "type": "2",
        "totstroke": 0,
        "stroke": 9,
        "isin": 0,
        "dic": "미"
    },
    {
        "rnum": 0,
        "cd": "25ed3",
        "ex": 0,
        "ineum": "",
        "in": "",
        "em": 0,
        "rad_id": 119,
        "type": "2",
        "totstroke": 0,
        "stroke": 9,
        "isin": 0,
        "dic": "자"
    },
    {
        "rnum": 0,
        "cd": "25ed4",
        "ex": 0,
        "ineum": "",
        "in": "",
        "em": 0,
        "rad_id": 119,
        "type": "2",
        "totstroke": 0,
        "stroke": 9,
        "isin": 0,
        "dic": "분"
    },
    {
        "rnum": 0,
        "cd": "25edf",
        "ex": 0,
        "ineum": "",
        "in": "",
        "em": 0,
        "rad_id": 119,
        "type": "2",
        "totstroke": 0,
        "stroke": 9,
        "isin": 0,
        "dic": "나"
    },
    {
        "rnum": 0,
        "cd": "f1390",
        "ex": 0,
        "ineum": "",
        "in": "",
        "em": 0,
        "rad_id": 119,
        "type": "F",
        "totstroke": 0,
        "stroke": 9,
        "isin": 0,
        "dic": "찬"
    },
    {
        "rnum": 0,
        "cd": "f145e",
        "ex": 0,
        "ineum": "",
        "in": "",
        "em": 0,
        "rad_id": 119,
        "type": "F",
        "totstroke": 0,
        "stroke": 9,
        "isin": 0,
        "dic": "춘"
    },
    {
        "rnum": 0,
        "cd": "f17f3",
        "ex": 0,
        "ineum": "",
        "in": "",
        "em": 0,
        "rad_id": 119,
        "type": "F",
        "totstroke": 0,
        "stroke": 9,
        "isin": 0,
        "dic": "휘"
    },
    {
        "rnum": 0,
        "cd": "f1ada",
        "ex": 0,
        "ineum": "",
        "in": "",
        "em": 0,
        "rad_id": 119,
        "type": "F",
        "totstroke": 0,
        "stroke": 9,
        "isin": 0,
        "dic": "나"
    },
    {
        "rnum": 0,
        "cd": "f1d96",
        "ex": 0,
        "ineum": "",
        "in": "",
        "em": 0,
        "rad_id": 119,
        "type": "F",
        "totstroke": 0,
        "stroke": 9,
        "isin": 0,
        "dic": "미"
    },
    {
        "rnum": 0,
        "cd": "f27f0",
        "ex": 0,
        "ineum": "",
        "in": "",
        "em": 0,
        "rad_id": 119,
        "type": "F",
        "totstroke": 0,
        "stroke": 9,
        "isin": 0,
        "dic": "정"
    }
]