[
    {
        "rnum": 0,
        "cd": "0908e",
        "ex": 0,
        "ineum": "",
        "in": "",
        "em": 0,
        "rad_id": 162,
        "type": "0",
        "totstroke": 0,
        "stroke": 17,
        "isin": 0,
        "dic": "요,유 : 빨리갈(요)"
    },
    {
        "rnum": 0,
        "cd": "28642",
        "ex": 0,
        "ineum": "",
        "in": "",
        "em": 0,
        "rad_id": 162,
        "type": "2",
        "totstroke": 0,
        "stroke": 17,
        "isin": 0,
        "dic": "요"
    },
    {
        "rnum": 0,
        "cd": "28643",
        "ex": 0,
        "ineum": "",
        "in": "",
        "em": 0,
        "rad_id": 162,
        "type": "2",
        "totstroke": 0,
        "stroke": 17,
        "isin": 0,
        "dic": "요"
    },
    {
        "rnum": 0,
        "cd": "28644",
        "ex": 0,
        "ineum": "",
        "in": "",
        "em": 0,
        "rad_id": 162,
        "type": "2",
        "totstroke": 0,
        "stroke": 17,
        "isin": 0,
        "dic": "약"
    },
    {
        "rnum": 0,
        "cd": "28645",
        "ex": 0,
        "ineum": "",
        "in": "",
        "em": 0,
        "rad_id": 162,
        "type": "2",
        "totstroke": 0,
        "stroke": 17,
        "isin": 0,
        "dic": "원"
    },
    {
        "rnum": 0,
        "cd": "28646",
        "ex": 0,
        "ineum": "",
        "in": "",
        "em": 0,
        "rad_id": 162,
        "type": "2",
        "totstroke": 0,
        "stroke": 17,
        "isin": 0,
        "dic": "돈"
    },
    {
        "rnum": 0,
        "cd": "28651",
        "ex": 0,
        "ineum": "",
        "in": "",
        "em": 0,
        "rad_id": 162,
        "type": "2",
        "totstroke": 0,
        "stroke": 17,
        "isin": 0,
        "dic": "궤"
    },
    {
        "rnum": 0,
        "cd": "28652",
        "ex": 0,
        "ineum": "",
        "in": "",
        "em": 0,
        "rad_id": 162,
        "type": "2",
        "totstroke": 0,
        "stroke": 17,
        "isin": 0,
        "dic": "익"
    },
    {
        "rnum": 0,
        "cd": "f1c26",
        "ex": 0,
        "ineum": "",
        "in": "",
        "em": 0,
        "rad_id": 162,
        "type": "F",
        "totstroke": 0,
        "stroke": 17,
        "isin": 0,
        "dic": "란"
    }
]